wsl_port_forwarding/__init__.py
wsl_port_forwarding/port_forwarding.py
WSL_Port_Forwarding-1.0.5b1.dist-info/LICENSE
WSL_Port_Forwarding-1.0.5b1.dist-info/METADATA
WSL_Port_Forwarding-1.0.5b1.dist-info/WHEEL
WSL_Port_Forwarding-1.0.5b1.dist-info/entry_points.txt
WSL_Port_Forwarding-1.0.5b1.dist-info/top_level.txt
WSL_Port_Forwarding-1.0.5b1.dist-info/RECORD
