Metadata-Version: 2.1
Name: WSL-Port-Forwarding
Version: 1.0.5b1
Summary: A script that enable outside program access WSL2 ports by port forwarding.
Home-page: https://github.com/ColorsWind/WSL-Port-Forwarding
Author: ColorsWind
Author-email: colors_wind@outlook.com
Project-URL: Bug Tracker, https://github.com/ColorsWind/WSL-Port-Forwarding/issues
Classifier: Programming Language :: Python :: 3
Classifier: License :: OSI Approved :: MIT License
Classifier: Operating System :: POSIX :: Linux
Requires-Python: >=3.6
License-File: LICENSE
